{
  "Header": {
    "title": "UNAMarket",
    "paragraph": "Sabores Universitarios, Entregas Rapidas"
  },
  "About": {
    "paragraph": "Nuestra misión es empoderar a los estudiantes de la UNAM mediante la creación de una plataforma innovadora que promueve el comercio local y ofrece una alternativa económica sostenible. Facilitamos la venta y distribución de comida casera hecha por estudiantes, utilizando los recursos de transporte del campus para garantizar entregas rápidas y eficientes.",
    "Why": [
      "Entrega rápida y eficiente",
      "Red de apoyo a estudiantes",
      "Comida casera",
      "Comercio local"
    ],
    "Why2": [
      "Creador de tu horario",
      "Facil de usar",
      "Variedad de platillos",
      "Confiable"
    ]
  },
  "Gallery": [
    {
      "title": "Project Title",
      "largeImage": "img/portfolio/01-large.jpg",
      "smallImage": "img/portfolio/01-small.jpg"
    },
    {
      "title": "Project Title",
      "largeImage": "img/portfolio/02-large.jpg",
      "smallImage": "img/portfolio/02-small.jpg"
    },
    {
      "title": "Project Title",
      "largeImage": "img/portfolio/03-large.jpg",
      "smallImage": "img/portfolio/03-small.jpg"
    },
    {
      "title": "Project Title",
      "largeImage": "img/portfolio/04-large.jpg",
      "smallImage": "img/portfolio/04-small.jpg"
    },
    {
      "title": "Project Title",
      "largeImage": "img/portfolio/05-large.jpg",
      "smallImage": "img/portfolio/05-small.jpg"
    },
    {
      "title": "Project Title",
      "largeImage": "img/portfolio/06-large.jpg",
      "smallImage": "img/portfolio/06-small.jpg"
    },
    {
      "title": "Project Title",
      "largeImage": "img/portfolio/07-large.jpg",
      "smallImage": "img/portfolio/07-small.jpg"
    },
    {
      "title": "Project Title",
      "largeImage": "img/portfolio/08-large.jpg",
      "smallImage": "img/portfolio/08-small.jpg"
    },
    {
      "title": "Project Title",
      "largeImage": "img/portfolio/09-large.jpg",
      "smallImage": "img/portfolio/09-small.jpg"
    }
  ],
  "Services": [
    {
      "icon": "fa fa-wordpress",
      "name": "Uno",
      "text": "Ser la plataforma líder en la UNAM que impulsa el emprendimiento estudiantil."
    },
    {
      "icon": "fa fa-cart-arrow-down",
      "name": "Dos",
      "text": "Promover el comercio local y fortalecer la comunidad universitaria."
    },
    {
      "icon": "fa fa-cloud-download",
      "name": "Tres",
      "text": "Mejorar la calidad de vida de los estudiantes con soluciones prácticas.."
    },
    {
      "icon": "fa fa-language",
      "name": "Cuatro",
      "text": "Ser un modelo de innovación, sostenibilidad y economía colaborativa."
    },
    {
      "icon": "fa fa-plane",
      "name": "Cinco",
      "text": "Combinar tecnología y educación para generar impacto positivo."
    },
    {
      "icon": "fa fa-pie-chart",
      "name": "Seis",
      "text": "Fomentar prácticas responsables que beneficien a la universidad y al medio ambiente."
    }
  ],
  "Testimonials": [
    {
      "img": "img/testimonials/01.jpg",
      "text": "\"Gracias a esta plataforma, siempre puedo pedir comida deliciosa y casera sin gastar de más. ¡Ideal para todo tipo de personas!\"",
      "name": "Rodrigo Sanchez"
    },
    {
      "img": "img/testimonials/02.jpg",
      "text": "\"La aplicación es súper intuitiva. En unos cuantos clics ya tengo mi pedido confirmado, y siempre llega a tiempo.\"",
      "name": "Ethan Sanchez"
    },
    {
      "img": "img/testimonials/03.jpg",
      "text": "\"Como estudiante, encontré en esta plataforma una oportunidad para vender mi comida casera. Ha sido una gran ayuda económica.\"",
      "name": "Aaron Jimenez"
    },
    {
      "img": "img/testimonials/04.jpg",
      "text": "\"Nunca había sido tan fácil acceder a comida rica, económica y hecha por otros estudiantes. ¡Es increíble apoyar a mi comunidad!\"",
      "name": "Alison Becerra"
    },
    {
      "img": "img/testimonials/05.jpg",
      "text": "\"La app no solo me ha ayudado a ahorrar dinero, sino también tiempo. Siempre recibo comida fresca y justo cuando la necesito.\"",
      "name": "Antonio Kernell"
    },
    {
      "img": "img/testimonials/06.jpg",
      "text": "\"Empecé vendiendo postres aquí, y ahora puedo cubrir varios de mis gastos como estudiante. ¡Es una idea brillante!\"",
      "name": "Sofia Benitez"
    }
  ],
  "Team": [
    {
      "img": "img/team/01.jpg",
      "name": "Mario Alberto Rocha Salazar",
      "job": "Quality Engineer"
    },
    {
      "img": "img/team/02.jpg",
      "name": "Asahel Said Main Cerezo",
      "job": "Software Architect"
    },
    {
      "img": "img/team/03.jpg",
      "name": "Laura Itzel Rodríguez Dimayuga",
      "job": "Project Leader"
    },
    {
      "img": "img/team/04.jpg",
      "name": "Cielo López Villalba",
      "job": "Communication Leader"
    }
  ],
  "Contact": {
    "address": "Ciudad Universitaria, CDMX, México",
    "phone": "+55 1234 5678",
    "email": "unamarket@unam.com.mx",
    "facebook": "facebook/UNAMarket.com",
    "twitter": "twitter/UNAMarket.com",
    "youtube": "youtube/UNAMarket.com"
  },
  "Features": [
    {
      "icon": "fa fa-comments-o",
      "title": "Sostenibilidad",
      "text": "Innovación. sostenibilidad y apoyo mutuo. Utilizamos el transporte público"
    },
    {
      "icon": "fa fa-bullhorn",
      "title": "Solidaridad",
      "text": "Fomentando la solidaridad y el emprendimiento dentro del campus universitario."
    },
    {
      "icon": "fa fa-group",
      "title": "Comunidad",
      "text": "Comunidad solidaria, emprendimiento estudiantil, economia colaborativa en UNAM"
    },
    {
      "icon": "fa fa-magic",
      "title": "Conciencia Social",
      "text": "Nos dirigimos a todo tipo de estudiantes, funcionando como una red de apoyo y oportunidades."
    }
  ]
}
